tipfyrecipes
