Metadata-Version: 1.0
Name: tipfyrecipes
Version: 0.3
Summary: Buildout recipes for Tipfy web framework
Home-page: http://code.google.com/p/tipfyrecipes/
Author: Carlo Pires
Author-email: carlopires@gmail.com
License: BSD
Keywords: buildout recipe google app engine appengine gae zc.buildout tipfy
Platform: any
Classifier: Development Status :: 4 - Beta
Classifier: Framework :: Buildout
Classifier: Intended Audience :: Developers
Classifier: License :: OSI Approved :: Apache Software License
Classifier: Topic :: Software Development :: Build Tools
Classifier: Topic :: Software Development :: Libraries :: Python Modules
